knowledge_extractor/__init__.py
knowledge_extractor/_nbdev.py
knowledge_extractor/keyword_generators.py
knowledge_extractor/tokens_ke.py
knowledge_extractor-0.0.2.dist-info/LICENSE
knowledge_extractor-0.0.2.dist-info/METADATA
knowledge_extractor-0.0.2.dist-info/WHEEL
knowledge_extractor-0.0.2.dist-info/entry_points.txt
knowledge_extractor-0.0.2.dist-info/top_level.txt
knowledge_extractor-0.0.2.dist-info/RECORD
